figonacci.py
figonacci-0.1.1.dist-info/METADATA
figonacci-0.1.1.dist-info/WHEEL
figonacci-0.1.1.dist-info/RECORD
