Metadata-Version: 2.1
Name: figonacci
Version: 0.1.1
Summary: Calculates figonacci numbers
Author: Nicolaj Figaw
Author-email: you@example.com
Requires-Python: >=3.11.2,<4.0.0
Classifier: Programming Language :: Python :: 3
